<chromosome id="13691" primary-parent-id="9437"><neuron id="0" type="in" activation="linear"/>
<neuron id="1" type="in" activation="linear"/>
<neuron id="2" type="in" activation="linear"/>
<neuron id="3" type="out" activation="sigmoid"/>
<connection id="4" src-id="0" dest-id="3" weight="-1.784418403576101"/>
<neuron id="167" type="hid" activation="sigmoid"/>
<connection id="168" src-id="0" dest-id="167" weight="-4.380636150782963"/>
<neuron id="296" type="hid" activation="sigmoid"/>
<neuron id="425" type="hid" activation="sigmoid"/>
<connection id="426" src-id="296" dest-id="425" weight="4.050773692523678"/>
<connection id="427" src-id="425" dest-id="3" weight="0.4113576232323787"/>
<connection id="554" src-id="2" dest-id="425" weight="0.6341745853424072"/>
<neuron id="560" type="hid" activation="sigmoid"/>
<connection id="562" src-id="560" dest-id="3" weight="-11.031951535192327"/>
<connection id="685" src-id="296" dest-id="560" weight="0.463195787742827"/>
<neuron id="690" type="hid" activation="sigmoid"/>
<connection id="691" src-id="167" dest-id="690" weight="-1.3843117125252493"/>
<neuron id="693" type="hid" activation="sigmoid"/>
<connection id="694" src-id="2" dest-id="693" weight="-1.7868917828033648"/>
<neuron id="962" type="hid" activation="sigmoid"/>
<connection id="963" src-id="1" dest-id="962" weight="-0.8846205148866619"/>
<neuron id="1476" type="hid" activation="sigmoid"/>
<connection id="1477" src-id="962" dest-id="1476" weight="2.2795163541017653"/>
<connection id="1478" src-id="1476" dest-id="3" weight="-0.46579627448832606"/>
<neuron id="2698" type="hid" activation="sigmoid"/>
<connection id="2699" src-id="693" dest-id="2698" weight="-2.1611000573676336"/>
<connection id="2700" src-id="2698" dest-id="296" weight="14.882575143390245"/>
<neuron id="3403" type="hid" activation="sigmoid"/>
<connection id="3404" src-id="690" dest-id="3403" weight="1.26345306471345"/>
<neuron id="3707" type="hid" activation="sigmoid"/>
<connection id="3708" src-id="3403" dest-id="3707" weight="0.5100901532896132"/>
<connection id="3709" src-id="3707" dest-id="560" weight="-0.24610496133176252"/>
<connection id="3841" src-id="690" dest-id="962" weight="0.528376971451947"/>
<connection id="6065" src-id="2698" dest-id="425" weight="-0.4349955774910633"/>
<connection id="8523" src-id="2698" dest-id="690" weight="-2.0579711272954704"/>
</chromosome>