<chromosome id="13625" primary-parent-id="9877"><neuron id="0" type="in" activation="linear"/>
<neuron id="1" type="in" activation="linear"/>
<neuron id="2" type="in" activation="linear"/>
<neuron id="3" type="out" activation="sigmoid"/>
<connection id="6" src-id="2" dest-id="3" weight="-5.3941759323868315"/>
<neuron id="167" type="hid" activation="sigmoid"/>
<neuron id="296" type="hid" activation="sigmoid"/>
<neuron id="425" type="hid" activation="sigmoid"/>
<connection id="426" src-id="296" dest-id="425" weight="6.135987912929463"/>
<connection id="427" src-id="425" dest-id="3" weight="-1.6834186330265666"/>
<connection id="556" src-id="2" dest-id="167" weight="0.1644022940078308"/>
<neuron id="557" type="hid" activation="sigmoid"/>
<connection id="558" src-id="0" dest-id="557" weight="3.5788684294361834"/>
<neuron id="560" type="hid" activation="sigmoid"/>
<connection id="561" src-id="167" dest-id="560" weight="-0.836335407448618"/>
<connection id="689" src-id="557" dest-id="3" weight="-2.406413498732373"/>
<neuron id="693" type="hid" activation="sigmoid"/>
<connection id="694" src-id="2" dest-id="693" weight="-5.176357055914169"/>
<connection id="695" src-id="693" dest-id="296" weight="3.135234336970493"/>
<connection id="821" src-id="560" dest-id="425" weight="-5.160009852759823"/>
<neuron id="959" type="hid" activation="sigmoid"/>
<connection id="960" src-id="560" dest-id="959" weight="-0.34584692400348865"/>
<connection id="961" src-id="959" dest-id="3" weight="-2.3151631754995963"/>
<neuron id="962" type="hid" activation="sigmoid"/>
<connection id="963" src-id="1" dest-id="962" weight="-4.74365241898148"/>
<connection id="964" src-id="962" dest-id="3" weight="-1.6425315737151953"/>
<connection id="1604" src-id="693" dest-id="167" weight="-0.7238566745974055"/>
<neuron id="3701" type="hid" activation="sigmoid"/>
<connection id="3702" src-id="557" dest-id="3701" weight="2.356737396406588"/>
<connection id="3703" src-id="3701" dest-id="167" weight="-4.917800194650141"/>
</chromosome>